authlib_httpx/__init__.py
authlib_httpx/assertion_client.py
authlib_httpx/oauth1_client.py
authlib_httpx/oauth2_client.py
authlib_httpx/utils.py
authlib_httpx-0.1.1.dist-info/LICENSE
authlib_httpx-0.1.1.dist-info/METADATA
authlib_httpx-0.1.1.dist-info/WHEEL
authlib_httpx-0.1.1.dist-info/top_level.txt
authlib_httpx-0.1.1.dist-info/RECORD
